podbase/__init__.py
podbase/podbase.py
podbase/types.py
podbase-0.0.1.dist-info/licenses/LICENSE
podbase-0.0.1.dist-info/METADATA
podbase-0.0.1.dist-info/WHEEL
podbase-0.0.1.dist-info/top_level.txt
podbase-0.0.1.dist-info/RECORD
