Metadata-Version: 2.4
Name: podbase
Version: 0.0.1
Summary: Python SDK for PodBase vector database
Author-email: usamaasfar <usama.asfar@outlook.com>
License-Expression: MIT
Project-URL: Homepage, https://github.com/usamaasfar/podbase
Project-URL: Repository, https://github.com/usamaasfar/podbase.git
Project-URL: Issues, https://github.com/usamaasfar/podbase/issues
Keywords: podbase,vector-database,python,sdk
Classifier: Development Status :: 3 - Alpha
Classifier: Intended Audience :: Developers
Classifier: Programming Language :: Python :: 3
Classifier: Programming Language :: Python :: 3.12
Requires-Python: >=3.12
License-File: LICENSE
Requires-Dist: httpx>=0.27.0
Provides-Extra: dev
Requires-Dist: pytest>=8.0.0; extra == "dev"
Requires-Dist: pytest-asyncio>=0.23.0; extra == "dev"
Requires-Dist: build>=1.0.0; extra == "dev"
Dynamic: license-file
